ca_certificates/__init__.py
ansiblebit_launchpad_ppa_webupd8-1.0.0.dist-info/METADATA
ansiblebit_launchpad_ppa_webupd8-1.0.0.dist-info/WHEEL
ansiblebit_launchpad_ppa_webupd8-1.0.0.dist-info/top_level.txt
ansiblebit_launchpad_ppa_webupd8-1.0.0.dist-info/RECORD
