Metadata-Version: 2.4
Name: ansiblebit.launchpad-ppa-webupd8
Version: 1.0.0
Summary: Dummy ansiblebit.launchpad-ppa-webupd8 package for PyPI
Author-email: Your Name <you@example.com>
Requires-Python: >=3.7
